sentry_dingding/__init__.py
sentry_dingding/forms.py
sentry_dingding/plugin.py
i61_sentry_dingtalk-0.1.0.dist-info/METADATA
i61_sentry_dingtalk-0.1.0.dist-info/WHEEL
i61_sentry_dingtalk-0.1.0.dist-info/entry_points.txt
i61_sentry_dingtalk-0.1.0.dist-info/top_level.txt
i61_sentry_dingtalk-0.1.0.dist-info/RECORD
