Metadata-Version: 2.1
Name: i61-sentry-dingtalk
Version: 0.1.0
Summary: A Sentry extension which send errors stats to DingTalk
Home-page: UNKNOWN
Author: sankyutang
Author-email: tangjunkai@61info.cn
License: MIT
Keywords: sentry dingtalk
Platform: UNKNOWN
Requires-Dist: sentry (>=9.0.0)
Requires-Dist: requests
